// class version 50.0 (50)
// access flags 0x21
public class Address {

  // compiled from: Address.java

  // access flags 0x12
  private final Ljava/lang/String; street

  // access flags 0x12
  private final I houseNumber

  // access flags 0x2
  private Ljava/lang/String; phoneNumber

  // access flags 0x1
  public <init>(Ljava/lang/String;ILjava/lang/String;)V
   L0
    LINENUMBER 10 L0
    ALOAD 0
    INVOKESPECIAL java/lang/Object.<init> ()V
   L1
    LINENUMBER 11 L1
    ALOAD 0
    ALOAD 1
    PUTFIELD Address.street : Ljava/lang/String;
   L2
    LINENUMBER 12 L2
    ALOAD 0
    ILOAD 2
    PUTFIELD Address.houseNumber : I
   L3
    LINENUMBER 13 L3
    ALOAD 0
    ALOAD 3
    PUTFIELD Address.phoneNumber : Ljava/lang/String;
   L4
    LINENUMBER 14 L4
    RETURN
   L5
    LOCALVARIABLE this LAddress; L0 L5 0
    LOCALVARIABLE street Ljava/lang/String; L0 L5 1
    LOCALVARIABLE houseNumber I L0 L5 2
    LOCALVARIABLE phoneNumber Ljava/lang/String; L0 L5 3
    MAXSTACK = 2
    MAXLOCALS = 4

  // access flags 0x1
  public getStreet()Ljava/lang/String;
  @Lorg/jetbrains/immutability/annotations/Const;() // invisible
   L0
    LINENUMBER 18 L0
    ALOAD 0
    GETFIELD Address.street : Ljava/lang/String;
    ARETURN
   L1
    LOCALVARIABLE this LAddress; L0 L1 0
    MAXSTACK = 1
    MAXLOCALS = 1

  // access flags 0x1
  public getHouseNumber()I
  @Lorg/jetbrains/immutability/annotations/Const;() // invisible
   L0
    LINENUMBER 23 L0
    ALOAD 0
    GETFIELD Address.houseNumber : I
    IRETURN
   L1
    LOCALVARIABLE this LAddress; L0 L1 0
    MAXSTACK = 1
    MAXLOCALS = 1

  // access flags 0x1
  public getPhoneNumber()Ljava/lang/String;
  @Lorg/jetbrains/immutability/annotations/Const;() // invisible
   L0
    LINENUMBER 28 L0
    ALOAD 0
    GETFIELD Address.phoneNumber : Ljava/lang/String;
    ARETURN
   L1
    LOCALVARIABLE this LAddress; L0 L1 0
    MAXSTACK = 1
    MAXLOCALS = 1

  // access flags 0x1
  public setPhoneNumber(Ljava/lang/String;)V
   L0
    LINENUMBER 32 L0
    ALOAD 0
    ALOAD 1
    PUTFIELD Address.phoneNumber : Ljava/lang/String;
   L1
    LINENUMBER 33 L1
    RETURN
   L2
    LOCALVARIABLE this LAddress; L0 L2 0
    LOCALVARIABLE phoneNumber Ljava/lang/String; L0 L2 1
    MAXSTACK = 2
    MAXLOCALS = 2
}
